ngrok-1.7.0.dist-info/METADATA
ngrok-1.7.0.dist-info/WHEEL
ngrok-1.7.0.dist-info/entry_points.txt
ngrok-1.7.0.dist-info/licenses/LICENSE-APACHE
ngrok-1.7.0.dist-info/licenses/LICENSE-MIT
ngrok/__init__.py
ngrok/__main__.py
ngrok/mypy.ini
ngrok/ngrok.abi3.so
ngrok/ngrok.pyi
ngrok/ngrok_parser.py
ngrok/py.typed
ngrok-1.7.0.dist-info/RECORD
