Metadata-Version: 2.4
Name: ngrok
Version: 1.7.0
Classifier: Development Status :: 5 - Production/Stable
Classifier: Intended Audience :: Developers
Classifier: License :: OSI Approved :: MIT License
Classifier: Operating System :: POSIX
Classifier: Operating System :: Microsoft :: Windows
Classifier: Operating System :: MacOS :: MacOS X
Classifier: Topic :: Utilities
Classifier: Programming Language :: Python
Classifier: Programming Language :: Python :: 3
Classifier: Programming Language :: Python :: 3 :: Only
Classifier: Programming Language :: Python :: 3.12
Classifier: Programming Language :: Python :: 3.13
Classifier: Topic :: System :: Networking
Classifier: Topic :: System :: Networking :: Firewalls
License-File: LICENSE-APACHE
License-File: LICENSE-MIT
Summary: The ngrok Agent SDK for Python
Keywords: ngrok,python,pypi,pyo3,ingress,networking
License: MIT OR Apache-2.0
Requires-Python: >=3.12
Project-URL: homepage, https://ngrok.com
Project-URL: repository, https://github.com/ngrok/ngrok-python
Project-URL: changelog, https://github.com/ngrok/ngrok-python/blob/main/CHANGELOG.md
